scfeatureprofiler/__init__.py
scfeatureprofiler/_core.py
scfeatureprofiler/_engine.py
scfeatureprofiler/_logging.py
scfeatureprofiler/_selection_marker.py
scfeatureprofiler/_stability.py
scfeatureprofiler/_utils.py
scfeatureprofiler/api.py
scfeatureprofiler/cli.py
scfeatureprofiler-1.1.2.dist-info/licenses/LICENSE
scfeatureprofiler-1.1.2.dist-info/METADATA
scfeatureprofiler-1.1.2.dist-info/WHEEL
scfeatureprofiler-1.1.2.dist-info/entry_points.txt
scfeatureprofiler-1.1.2.dist-info/top_level.txt
scfeatureprofiler-1.1.2.dist-info/RECORD
