Metadata-Version: 2.4
Name: scfeatureprofiler
Version: 1.1.2
Summary: A powerful, multi-interface Python package for deep characterization of single-cell feature expression patterns.
Author: Qingzhou Zhang
License-Expression: MIT
Classifier: Development Status :: 4 - Beta
Classifier: Intended Audience :: Science/Research
Classifier: Programming Language :: Python :: 3
Classifier: Programming Language :: Python :: 3.9
Classifier: Programming Language :: Python :: 3.10
Classifier: Programming Language :: Python :: 3.11
Classifier: Programming Language :: Python :: 3.12
Classifier: Topic :: Scientific/Engineering :: Bio-Informatics
Requires-Python: >=3.9
License-File: LICENSE
Requires-Dist: numpy>=1.20.0
Requires-Dist: pandas>=1.3.0
Requires-Dist: scipy>=1.7.0
Requires-Dist: statsmodels>=0.13.0
Requires-Dist: joblib>=1.2.0
Requires-Dist: typer>=0.9.0
Requires-Dist: scanpy>=1.9.0
Provides-Extra: anndata
Requires-Dist: anndata>=0.8.0; extra == "anndata"
Provides-Extra: dev
Requires-Dist: black>=22.0.0; extra == "dev"
Requires-Dist: ruff>=0.1.0; extra == "dev"
Requires-Dist: mypy>=1.0.0; extra == "dev"
Requires-Dist: pytest>=7.0.0; extra == "dev"
Requires-Dist: pytest-cov>=4.0.0; extra == "dev"
Provides-Extra: docs
Requires-Dist: sphinx>=5.0.0; extra == "docs"
Requires-Dist: sphinx-rtd-theme>=1.0.0; extra == "docs"
Requires-Dist: numpydoc>=1.5.0; extra == "docs"
Provides-Extra: all
Requires-Dist: scfeatureprofiler[dev]; extra == "all"
Requires-Dist: scfeatureprofiler[docs]; extra == "all"
Dynamic: license-file
